[
  {
    "country": "United States",
    "title": "Celtics",
    "pubDate": "Tue, 21 May 2024 16:00:00 -0700",
    "picture": "https://t2.gstatic.com/images?q=tbn:ANd9GcTK-U9VMULy0M7k1ORUCWmH9wPTU_0qIt5J--S8R_rDYhpNJBRk1lAetHNUM6JbOCnvOarhjCXK",
    "news_item_snippet": "The Indiana Pacers face the Boston Celtics in Game 1 of the NBA Eastern Conference Finals. Here&#39;s how to watch.",
    "news_item_url": "https://www.cbsnews.com/essentials/how-to-watch-the-indiana-pacers-vs-boston-celtics-nba-playoffs-game-1/",
    "picture_source": "Indy Cornrows",
    "approx_traffic": "500,000+"
  },
  {
    "country": "United States",
    "title": "Austin Maddox",
    "pubDate": "Mon, 20 May 2024 17:00:00 -0700",
    "picture": "https://t1.gstatic.com/images?q=tbn:ANd9GcR2W18_82ZxdElAXLoxtQkFA7PEDsA7JHAI2Prn2N0N4FaFw6ODCIfA034FlBcjCk5e7XANeKk7",
    "news_item_snippet": "Maddox was one of 27 people arrested as part of a multi-agency operation late last month, Jacksonville Sheriff T.K. Waters said.",
    "news_item_url": "https://ny1.com/nyc/all-boroughs/sports/2024/05/21/former-red-sox-pitcher-austin-maddox-arrested-underage-sex-sting",
    "picture_source": "News 5 Cleveland",
    "approx_traffic": "200,000+"
  },
  {
    "country": "India",
    "title": "HSC Result 2024",
    "pubDate": "Tue, 21 May 2024 11:30:00 +0530",
    "picture": "https://t3.gstatic.com/images?q=tbn:ANd9GcQjI8qQYugcg75YIUqhzmK00SDP4Em0uSF9dDXdJKUeFIRc3cB3FPtS2tH9_ztYplxxRw0Je9Ku",
    "news_item_snippet": "Maharashtra Board HSC 12th Result 2024: \u092e\u0939\u093e\u0930\u093e\u0937\u094d\u091f\u094d\u0930 \u0938\u094d\u091f\u0947\u091f \u092c\u094b\u0930\u094d\u0921 \u0911\u092b \u0938\u0947\u0915\u0947\u0902\u0921\u0930\u0940 \u090f\u0902\u0921 \u0939\u093e\u092f\u0930 \u0938\u0947\u0915\u0947\u0902\u0921\u0930\u0940 \u090f\u091c\u0941\u0915\u0947\u0936\u0928 (MSBSHSE) \u0915\u0940 \u0913\u0930 \u0938\u0947 \u0906\u091c \u092e\u0939\u093e\u0930\u093e\u0937\u094d\u091f\u094d\u0930&nbsp;...",
    "news_item_url": "https://ndtv.in/career/msbshse-maharashtra-board-hsc-class-12th-result-declared-on-mahresult-nic-in-check-here-from-direct-link-5711199",
    "picture_source": "Hindustan \u0939\u093f\u0902\u0926\u0940",
    "approx_traffic": "500,000+"
  },
  {
    "country": "India",
    "title": "SRH vs KKR",
    "pubDate": "Mon, 20 May 2024 09:30:00 +0530",
    "picture": "https://t0.gstatic.com/images?q=tbn:ANd9GcRXmqzAuSSGuMko2GiEvlcWOY_KPqeDoEAiqjLBSukQeciavH7yzs3caO8QupnjsiJP4QxpgPc1",
    "news_item_snippet": "KKR vs SRH Highlights, IPL 2024 Qualifier 1: Kolkata Knight Riders thrash Sunrisers Hyderabad in the Qualifier 1 match of IPL 2024.",
    "news_item_url": "https://sports.ndtv.com/ipl-2024/kkr-vs-srh-live-match-score-indian-premier-league-2024-qualifier-1-kolkata-knight-riders-vs-sunrisers-hyderabad-live-match-updates-5712993",
    "picture_source": "NDTVSports.com",
    "approx_traffic": "2,000,000+"
  },
  {
    "country": "India",
    "title": "KKR vs SRH",
    "pubDate": "Mon, 20 May 2024 02:30:00 +0530",
    "picture": "https://t0.gstatic.com/images?q=tbn:ANd9GcTIFgsuVN8OgQN-pHYhgVjCgkiu7ZBL3RWWN9YRhYzUTd36dG6nWgBXJScQe_0ZuAjDvDYfEJxF",
    "news_item_snippet": "IPL Qualifier 1 2024: \u0906\u0908\u092a\u0940\u090f\u0932 2024 \u0915\u093e \u092a\u0939\u0932\u093e \u0915\u094d\u0935\u093e\u0932\u0940\u092b\u093c\u093e\u092f\u0930 \u0915\u094b\u0932\u0915\u093e\u0924\u093e \u0928\u093e\u0907\u091f \u0930\u093e\u0907\u0921\u0930\u094d\u0938 \u0914\u0930 \u0938\u0928\u0930\u093e\u0907\u091c\u0930\u094d\u0938 \u0939\u0948\u0926\u0930\u093e\u092c\u093e\u0926 \u0915\u0947 \u092c\u0940\u091a \u0906\u091c \u0926\u0941\u0928\u093f\u092f\u093e \u0915\u0947 \u0938\u092c\u0938\u0947 \u092c\u0921\u093c\u0947&nbsp;...",
    "news_item_url": "https://www.jagranjosh.com/general-knowledge/kkr-vs-srh-team-squad-probable-playing-11-match-time-today-venue-and-where-to-watch-1716235533-2",
    "picture_source": "\u0905\u092e\u0930 \u0909\u091c\u093e\u0932\u093e",
    "approx_traffic": "500,000+"
  },
  {
    "country": "Brazil",
    "title": "Bragantino x Sousa",
    "pubDate": "Tue, 21 May 2024 06:00:00 -0500",
    "picture": "https://t0.gstatic.com/images?q=tbn:ANd9GcQeUuzwmwpF7zl8iFlPysC2VSdkcip2WrQcAxTs54J8Fw4LUkRC0q0c8lItgolxsQkx6Sw3Hhve",
    "news_item_snippet": "Fim do Jogo, RB Bragantino 3, Sousa EC 0. 2\u00ba Tempo.",
    "news_item_url": "https://www.terra.com.br/esportes/futebol/copa-do-brasil/ao-vivo/bragantino-x-sousa-ec/84104/",
    "picture_source": "globoesporte.com",
    "approx_traffic": "200,000+"
  },
  {
    "country": "Spain",
    "title": "Toni Kroos",
    "pubDate": "Tue, 21 May 2024 14:00:00 +0200",
    "picture": "https://t3.gstatic.com/images?q=tbn:ANd9GcQ9V6YZddVUOvrMVjMMm1FUnFFqNO7uFioiBYmRRWvyytT_p-VrtH_cL4gtPJdwnsc1KebFg6SO",
    "news_item_snippet": "&quot;Cuando se retire, quiero que lo haga de coraz\u00f3n&quot;. Esta fue la frase que la madre de Toni Kroos, Birgit K\u00e4mmer (61), pronunci\u00f3 en un podcast.",
    "news_item_url": "https://www.elmundo.es/loc/famosos/2024/05/21/664ca6defdddff4a658b456d.html",
    "picture_source": "Real Madrid",
    "approx_traffic": "200,000+"
  },
  {
    "country": "United Kingdom",
    "title": "England squad",
    "pubDate": "Tue, 21 May 2024 12:00:00 +0100",
    "picture": "https://t1.gstatic.com/images?q=tbn:ANd9GcTrVA4LyDJFrkZ4qwkMitCpTyHDrpCkIJR_5f050XFUZsMusngJZoJ2g6HMBEEPEGvwYfnrtfol",
    "news_item_snippet": "Marcus Rashford and Jordan Henderson are left out of Gareth Southgate&#39;s provisional 33-man England squad for Euro 2024.",
    "news_item_url": "https://www.bbc.co.uk/sport/football/articles/c3gglr8mpzdo",
    "picture_source": "BBC Sport",
    "approx_traffic": "200,000+"
  }
]